yahooquery/__init__.py
yahooquery/base.py
yahooquery/constants.py
yahooquery/headless.py
yahooquery/misc.py
yahooquery/research.py
yahooquery/screener.py
yahooquery/session_management.py
yahooquery/ticker.py
yahooquery/utils.py
yahooquery-2.4.0.dist-info/METADATA
yahooquery-2.4.0.dist-info/WHEEL
yahooquery-2.4.0.dist-info/licenses/LICENSE.txt
yahooquery-2.4.0.dist-info/RECORD
