Metadata-Version: 2.4
Name: yahooquery
Version: 2.4.0
Summary: Python wrapper for an unofficial Yahoo Finance API
Author-email: Doug Guthrie <douglas.p.guthrie@gmail.com>
License: MIT
License-File: LICENSE.txt
Keywords: API,Yahoo Finance,finance,python,stocks
Requires-Python: <4.0,>=3.9
Requires-Dist: beautifulsoup4>=4.12.2
Requires-Dist: curl-cffi>=0.10.0
Requires-Dist: lxml>=4.9.3
Requires-Dist: pandas>=2.2.0
Requires-Dist: requests-futures>=1.0.1
Requires-Dist: tqdm>=4.65.0
Provides-Extra: dev
Requires-Dist: mkdocs-material>=9.6.0; extra == 'dev'
Requires-Dist: pre-commit>=4.2.0; extra == 'dev'
Requires-Dist: pytest-cov>=6.1.0; extra == 'dev'
Requires-Dist: pytest>=8.3.0; extra == 'dev'
Requires-Dist: ruff>=0.11.0; extra == 'dev'
Provides-Extra: premium
Requires-Dist: selenium>=4.32.0; extra == 'premium'
